{
    "5190801": {
        "tips": "놀이공원에 갑자기 통제를 벗어난 오리 로봇이 다수 나타났습니다. 이벤트 주최 측은 참가 선수들이 이 장난꾸러기들을 회수해 주기를 바라고 있습니다!",
        "name": "오리 파티",
        "monster_level": 80,
        "id": 5190801,
        "map": "5190801",
        "ai_level": 1,
        "background_1": "X66",
        "attribute_factor": [
            1000,
            1000,
            1000
        ],
        "hero_list": [
            [
                6112,
                611201
            ],
            [
                0,
                1
            ],
            [
                0,
                1
            ]
        ]
    },
    "5190802": {
        "tips": "놀이공원에 갑자기 통제를 벗어난 오리 로봇이 다수 나타났습니다. 이벤트 주최 측은 참가 선수들이 이 장난꾸러기들을 회수해 주기를 바라고 있습니다!",
        "name": "난동 부리는 오리-1",
        "monster_level": 80,
        "id": 5190802,
        "map": "5190802",
        "ai_level": 1,
        "background_1": "X66",
        "attribute_factor": [
            1000,
            1000,
            1000
        ],
        "hero_list": [
            [
                6112,
                611201
            ],
            [
                0,
                1
            ],
            [
                0,
                1
            ]
        ]
    },
    "5190803": {
        "tips": "놀이공원에 갑자기 통제를 벗어난 오리 로봇이 다수 나타났습니다. 이벤트 주최 측은 참가 선수들이 이 장난꾸러기들을 회수해 주기를 바라고 있습니다!",
        "name": "난동 부리는 오리-2",
        "monster_level": 80,
        "id": 5190803,
        "map": "5190803",
        "ai_level": 1,
        "background_1": "X66",
        "attribute_factor": [
            1000,
            1000,
            1000
        ],
        "hero_list": [
            [
                6112,
                611201
            ],
            [
                0,
                1
            ],
            [
                0,
                1
            ]
        ]
    },
    "5190804": {
        "tips": "놀이공원에 갑자기 통제를 벗어난 오리 로봇이 다수 나타났습니다. 이벤트 주최 측은 참가 선수들이 이 장난꾸러기들을 회수해 주기를 바라고 있습니다!",
        "name": "난동 부리는 오리-3",
        "monster_level": 80,
        "id": 5190804,
        "map": "5190804",
        "ai_level": 1,
        "background_1": "X66",
        "attribute_factor": [
            1000,
            1000,
            1000
        ],
        "hero_list": [
            [
                6112,
                611201
            ],
            [
                0,
                1
            ],
            [
                0,
                1
            ]
        ]
    },
    "5190805": {
        "tips": "놀이공원에 갑자기 통제를 벗어난 오리 로봇이 다수 나타났습니다. 이벤트 주최 측은 참가 선수들이 이 장난꾸러기들을 회수해 주기를 바라고 있습니다!",
        "name": "난동 부리는 오리-4",
        "monster_level": 80,
        "id": 5190805,
        "map": "5190805",
        "ai_level": 1,
        "background_1": "X66",
        "attribute_factor": [
            1000,
            1000,
            1000
        ],
        "hero_list": [
            [
                6112,
                611201
            ],
            [
                0,
                1
            ],
            [
                0,
                1
            ]
        ]
    },
    "5190806": {
        "tips": "놀이공원에 갑자기 통제를 벗어난 오리 로봇이 다수 나타났습니다. 이벤트 주최 측은 참가 선수들이 이 장난꾸러기들을 회수해 주기를 바라고 있습니다!",
        "name": "난동 부리는 오리-5",
        "monster_level": 80,
        "id": 5190806,
        "map": "5190806",
        "ai_level": 1,
        "background_1": "X66",
        "attribute_factor": [
            1000,
            1000,
            1000
        ],
        "hero_list": [
            [
                6112,
                611201
            ],
            [
                0,
                1
            ],
            [
                0,
                1
            ]
        ]
    },
    "5190807": {
        "tips": "놀이공원에 갑자기 통제를 벗어난 오리 로봇이 다수 나타났습니다. 이벤트 주최 측은 참가 선수들이 이 장난꾸러기들을 회수해 주기를 바라고 있습니다!",
        "name": "난동 부리는 오리-6",
        "monster_level": 80,
        "id": 5190807,
        "map": "5190807",
        "ai_level": 1,
        "background_1": "X66",
        "attribute_factor": [
            1000,
            1000,
            1000
        ],
        "hero_list": [
            [
                6112,
                611201
            ],
            [
                0,
                1
            ],
            [
                0,
                1
            ]
        ]
    },
    "5190808": {
        "tips": "놀이공원에 갑자기 통제를 벗어난 오리 로봇이 다수 나타났습니다. 이벤트 주최 측은 참가 선수들이 이 장난꾸러기들을 회수해 주기를 바라고 있습니다!",
        "name": "난동 부리는 오리-7",
        "monster_level": 80,
        "id": 5190808,
        "map": "5190808",
        "ai_level": 1,
        "background_1": "X66",
        "attribute_factor": [
            1000,
            1000,
            1000
        ],
        "hero_list": [
            [
                6112,
                611201
            ],
            [
                0,
                1
            ],
            [
                0,
                1
            ]
        ]
    },
    "5190809": {
        "tips": "놀이공원에 갑자기 통제를 벗어난 오리 로봇이 다수 나타났습니다. 이벤트 주최 측은 참가 선수들이 이 장난꾸러기들을 회수해 주기를 바라고 있습니다!",
        "name": "난동 부리는 오리-8",
        "monster_level": 80,
        "id": 5190809,
        "map": "5190809",
        "ai_level": 1,
        "background_1": "X66",
        "attribute_factor": [
            1000,
            1000,
            1000
        ],
        "hero_list": [
            [
                6112,
                611201
            ],
            [
                0,
                1
            ],
            [
                0,
                1
            ]
        ]
    },
    "5190811": {
        "tips": "놀이공원에 갑자기 통제를 벗어난 오리 로봇이 다수 나타났습니다. 이벤트 주최 측은 참가 선수들이 이 장난꾸러기들을 회수해 주기를 바라고 있습니다!",
        "name": "오리 파티",
        "monster_level": 80,
        "id": 5190811,
        "map": "5190811",
        "ai_level": 1,
        "background_1": "X66",
        "attribute_factor": [
            1000,
            1000,
            1000
        ],
        "hero_list": [
            [
                6112,
                611201
            ],
            [
                0,
                1
            ],
            [
                0,
                1
            ]
        ]
    },
    "5190812": {
        "tips": "놀이공원에 갑자기 통제를 벗어난 오리 로봇이 다수 나타났습니다. 이벤트 주최 측은 참가 선수들이 이 장난꾸러기들을 회수해 주기를 바라고 있습니다!",
        "name": "행패 부리는 오리-1",
        "monster_level": 80,
        "id": 5190812,
        "map": "5190812",
        "ai_level": 1,
        "background_1": "X66",
        "attribute_factor": [
            1000,
            1000,
            1000
        ],
        "hero_list": [
            [
                6112,
                611201
            ],
            [
                0,
                1
            ],
            [
                0,
                1
            ]
        ]
    },
    "5190813": {
        "tips": "놀이공원에 갑자기 통제를 벗어난 오리 로봇이 다수 나타났습니다. 이벤트 주최 측은 참가 선수들이 이 장난꾸러기들을 회수해 주기를 바라고 있습니다!",
        "name": "행패 부리는 오리-2",
        "monster_level": 80,
        "id": 5190813,
        "map": "5190813",
        "ai_level": 1,
        "background_1": "X66",
        "attribute_factor": [
            1000,
            1000,
            1000
        ],
        "hero_list": [
            [
                6112,
                611201
            ],
            [
                0,
                1
            ],
            [
                0,
                1
            ]
        ]
    },
    "5190814": {
        "tips": "놀이공원에 갑자기 통제를 벗어난 오리 로봇이 다수 나타났습니다. 이벤트 주최 측은 참가 선수들이 이 장난꾸러기들을 회수해 주기를 바라고 있습니다!",
        "name": "행패 부리는 오리-3",
        "monster_level": 80,
        "id": 5190814,
        "map": "5190814",
        "ai_level": 1,
        "background_1": "X66",
        "attribute_factor": [
            1000,
            1000,
            1000
        ],
        "hero_list": [
            [
                6112,
                611201
            ],
            [
                0,
                1
            ],
            [
                0,
                1
            ]
        ]
    },
    "5190815": {
        "tips": "놀이공원에 갑자기 통제를 벗어난 오리 로봇이 다수 나타났습니다. 이벤트 주최 측은 참가 선수들이 이 장난꾸러기들을 회수해 주기를 바라고 있습니다!",
        "name": "행패 부리는 오리-4",
        "monster_level": 80,
        "id": 5190815,
        "map": "5190815",
        "ai_level": 1,
        "background_1": "X66",
        "attribute_factor": [
            1000,
            1000,
            1000
        ],
        "hero_list": [
            [
                6112,
                611201
            ],
            [
                0,
                1
            ],
            [
                0,
                1
            ]
        ]
    },
    "5190816": {
        "tips": "놀이공원에 갑자기 통제를 벗어난 오리 로봇이 다수 나타났습니다. 이벤트 주최 측은 참가 선수들이 이 장난꾸러기들을 회수해 주기를 바라고 있습니다!",
        "name": "행패 부리는 오리-5",
        "monster_level": 80,
        "id": 5190816,
        "map": "5190816",
        "ai_level": 1,
        "background_1": "X66",
        "attribute_factor": [
            1000,
            1000,
            1000
        ],
        "hero_list": [
            [
                6112,
                611201
            ],
            [
                0,
                1
            ],
            [
                0,
                1
            ]
        ]
    },
    "5190817": {
        "tips": "놀이공원에 갑자기 통제를 벗어난 오리 로봇이 다수 나타났습니다. 이벤트 주최 측은 참가 선수들이 이 장난꾸러기들을 회수해 주기를 바라고 있습니다!",
        "name": "행패 부리는 오리-6",
        "monster_level": 80,
        "id": 5190817,
        "map": "5190817",
        "ai_level": 1,
        "background_1": "X66",
        "attribute_factor": [
            1000,
            1000,
            1000
        ],
        "hero_list": [
            [
                6112,
                611201
            ],
            [
                0,
                1
            ],
            [
                0,
                1
            ]
        ]
    },
    "5190818": {
        "tips": "놀이공원에 갑자기 통제를 벗어난 오리 로봇이 다수 나타났습니다. 이벤트 주최 측은 참가 선수들이 이 장난꾸러기들을 회수해 주기를 바라고 있습니다!",
        "name": "행패 부리는 오리-7",
        "monster_level": 80,
        "id": 5190818,
        "map": "5190818",
        "ai_level": 1,
        "background_1": "X66",
        "attribute_factor": [
            1000,
            1000,
            1000
        ],
        "hero_list": [
            [
                6112,
                611201
            ],
            [
                0,
                1
            ],
            [
                0,
                1
            ]
        ]
    },
    "5190819": {
        "tips": "놀이공원에 갑자기 통제를 벗어난 오리 로봇이 다수 나타났습니다. 이벤트 주최 측은 참가 선수들이 이 장난꾸러기들을 회수해 주기를 바라고 있습니다!",
        "name": "행패 부리는 오리-8",
        "monster_level": 80,
        "id": 5190819,
        "map": "5190819",
        "ai_level": 1,
        "background_1": "X66",
        "attribute_factor": [
            1000,
            1000,
            1000
        ],
        "hero_list": [
            [
                6112,
                611201
            ],
            [
                0,
                1
            ],
            [
                0,
                1
            ]
        ]
    },
    "5190821": {
        "tips": "도전 모드를 진행하며 스테이지 시간이 대폭 제한된다. 임의 오리를 잡으면 7초의 시간 보상을 획득하며 이번 스테이지는 최대 15분 진행된다.",
        "name": "도전 모드",
        "monster_level": 80,
        "id": 5190821,
        "map": "5190821",
        "ai_level": 1,
        "background_1": "X66",
        "attribute_factor": [
            1000,
            1000,
            1000
        ],
        "hero_list": [
            [
                6112,
                611201
            ],
            [
                0,
                1
            ],
            [
                0,
                1
            ]
        ]
    },
    "all": [
        5190801,
        5190802,
        5190803,
        5190804,
        5190805,
        5190806,
        5190807,
        5190808,
        5190809,
        5190811,
        5190812,
        5190813,
        5190814,
        5190815,
        5190816,
        5190817,
        5190818,
        5190819,
        5190821
    ]
}