{
    "1": {
        "name": "파괴 경계",
        "stage_id": 1,
        "point_max": 96000,
        "personal_reward": [
            [
                40,
                60
            ],
            [
                52003,
                60
            ]
        ]
    },
    "2": {
        "name": "파괴 심층",
        "stage_id": 2,
        "point_max": 96000,
        "personal_reward": [
            [
                40,
                60
            ],
            [
                52003,
                60
            ]
        ]
    },
    "3": {
        "name": "교차 노드",
        "stage_id": 3,
        "point_max": 96000,
        "personal_reward": [
            [
                40,
                60
            ],
            [
                52003,
                60
            ]
        ]
    },
    "4": {
        "name": "교차 이역",
        "stage_id": 4,
        "point_max": 96000,
        "personal_reward": [
            [
                40,
                60
            ],
            [
                52003,
                60
            ]
        ]
    },
    "5": {
        "name": "은폐된 영역",
        "stage_id": 5,
        "point_max": 96000,
        "personal_reward": [
            [
                40,
                60
            ],
            [
                52003,
                60
            ]
        ]
    },
    "all": [
        1,
        2,
        3,
        4,
        5
    ]
}